{
  "timestamp": "2026-04-04T20:45:00Z",
  "buildType": "production",
  "pages": {
    "/login": {
      "lighthouse": {
        "performance": 94,
        "accessibility": 95,
        "best-practices": 100,
        "seo": 66
      },
      "performanceMetrics": {
        "fcp": 1367,
        "lcp": 2788,
        "tbt": 10,
        "cls": 0,
        "si": 3791
      },
      "axeViolations": {
        "critical": 0,
        "serious": 1,
        "details": ["aria-prohibited-attr on AnimatedWordmark span"]
      },
      "seoFailures": [
        "is-crawlable: noindex,nofollow meta tag",
        "robots.txt: Disallow /login"
      ],
      "performanceOpportunities": [
        "unused-javascript: 300ms savings"
      ]
    }
  }
}
